better_regressions/__init__.py
better_regressions/binned.py
better_regressions/classifier.py
better_regressions/eda.py
better_regressions/kernel.py
better_regressions/linear.py
better_regressions/piecewise.py
better_regressions/recency.py
better_regressions/scaling.py
better_regressions/smoothing.py
better_regressions/structure.py
better_regressions/tree_rendering.py
better_regressions/utils.py
better_regressions-0.9.0.dist-info/METADATA
better_regressions-0.9.0.dist-info/WHEEL
better_regressions-0.9.0.dist-info/licenses/LICENSE
better_regressions-0.9.0.dist-info/RECORD
