Metadata-Version: 2.4
Name: better-regressions
Version: 0.9.0
Summary: Advanced regression methods with sklearn-like interface
License: MIT
License-File: LICENSE
Requires-Python: >=3.10
Requires-Dist: beartype>=0.10.0
Requires-Dist: build>=1.2.2.post1
Requires-Dist: dcor>=0.6
Requires-Dist: factor-analyzer>=0.5.1
Requires-Dist: ipykernel>=6.29.5
Requires-Dist: ipywidgets>=8.1.7
Requires-Dist: jaxtyping>=0.2.11
Requires-Dist: lightgbm>=4.6.0
Requires-Dist: loguru>=0.7.3
Requires-Dist: matplotlib>=3.10.1
Requires-Dist: networkx>=3.4.2
Requires-Dist: numpy>=1.20.0
Requires-Dist: pandas>=2.2.3
Requires-Dist: plotly>=6.1.2
Requires-Dist: rich>=14.0.0
Requires-Dist: scikit-learn>=1.0.0
Requires-Dist: scipy>=1.7.0
Requires-Dist: seaborn>=0.13.2
Requires-Dist: setuptools>=78.1.0
Requires-Dist: supersmoother>=0.4
Requires-Dist: tqdm>=4.67.1
Requires-Dist: twine>=6.1.0
Requires-Dist: xgboost>=3.0.0
Provides-Extra: dev
Requires-Dist: black>=23.0.0; extra == 'dev'
Requires-Dist: isort>=5.12.0; extra == 'dev'
